qrutil/__init__.py
qrutil/dataprocess/NerProcesser.py
qrutil/dataprocess/__init__.py
qrutil/decorators/__init__.py
qrutil/decorators/info_decorator.py
qrutil/fileprocess/FileProcesser.py
qrutil/fileprocess/JsonlProcesser.py
qrutil/fileprocess/XlsxProcesser.py
qrutil/fileprocess/__init__.py
qrutil/loader/ConllLoader.py
qrutil/loader/Loader.py
qrutil/loader/__init__.py
qrutil/loader/checker.py
qrutils/__init__.py
qrutils/dataprocess/NerProcesser.py
qrutils/dataprocess/__init__.py
qrutils/decorators/__init__.py
qrutils/decorators/info_decorator.py
qrutils/fileprocess/FileProcesser.py
qrutils/fileprocess/JsonlProcesser.py
qrutils/fileprocess/XlsxProcesser.py
qrutils/fileprocess/__init__.py
qrutils/loader/ConllLoader.py
qrutils/loader/Loader.py
qrutils/loader/__init__.py
qrutils/loader/checker.py
qrutils-0.0.2.2.dist-info/METADATA
qrutils-0.0.2.2.dist-info/WHEEL
qrutils-0.0.2.2.dist-info/top_level.txt
qrutils-0.0.2.2.dist-info/RECORD
