Metadata-Version: 2.1
Name: qrutils
Version: 0.0.2.2
Summary: UNKNOWN
Home-page: UNKNOWN
Author: VictorT
License: UNKNOWN
Platform: UNKNOWN
Classifier: Development Status :: 3 - Alpha
Classifier: Intended Audience :: Developers
Classifier: Topic :: Software Development :: Build Tools
Classifier: License :: OSI Approved :: MIT License
Classifier: Programming Language :: Python :: 2
Classifier: Programming Language :: Python :: 2.7
Classifier: Programming Language :: Python :: 3
Classifier: Programming Language :: Python :: 3.3
Classifier: Programming Language :: Python :: 3.4
Classifier: Programming Language :: Python :: 3.5
Requires-Dist: pandas (==1.4.1)
Requires-Dist: setuptools (==58.0.4)
Requires-Dist: tqdm (==4.63.1)
Requires-Dist: XlsxWriter (==3.0.3)
